fusionlib/__init__.py
fusionlib-0.2.dist-info/METADATA
fusionlib-0.2.dist-info/WHEEL
fusionlib-0.2.dist-info/top_level.txt
fusionlib-0.2.dist-info/RECORD
